MontagePy/FreeSans.ttf
MontagePy/__init__.py
MontagePy/_wrappers.c
MontagePy/_wrappers.pypy38-pp73-x86_64-linux-gnu.so
MontagePy/main.c
MontagePy/main.pypy38-pp73-x86_64-linux-gnu.so
MontagePy/archive/__init__.py
MontagePy/archive/mArchiveDownload.py
MontagePy/archive/mArchiveList.py
montagepy-2.3.0.dist-info/LICENSE
montagepy-2.3.0.dist-info/METADATA
montagepy-2.3.0.dist-info/WHEEL
montagepy-2.3.0.dist-info/top_level.txt
montagepy-2.3.0.dist-info/RECORD
