Metadata-Version: 2.1
Name: MontagePy
Version: 2.3.0
Summary: Montage toolkit for reprojecting, mosaicking, and displaying astronomical images.
Author-email: John Good <jcg@ipac.caltech.edu>
License: 
Project-URL: Homepage, https://github.com/Caltech-IPAC/Montage
Keywords: astronomy,astronomical,image,reprojection,mosaic,visualization
License-File: LICENSE
Requires-Dist: requests
